google_datacatalog_apache_atlas_connector-0.6.0-py3.7-nspkg.pth
google/datacatalog_connectors/apache_atlas/__init__.py
google/datacatalog_connectors/apache_atlas/apache_atlas2datacatalog_cli.py
google/datacatalog_connectors/apache_atlas/prepare/__init__.py
google/datacatalog_connectors/apache_atlas/prepare/assembled_entry_factory.py
google/datacatalog_connectors/apache_atlas/prepare/constant.py
google/datacatalog_connectors/apache_atlas/prepare/datacatalog_attribute_normalizer.py
google/datacatalog_connectors/apache_atlas/prepare/datacatalog_entry_factory.py
google/datacatalog_connectors/apache_atlas/prepare/datacatalog_tag_factory.py
google/datacatalog_connectors/apache_atlas/prepare/datacatalog_tag_template_factory.py
google/datacatalog_connectors/apache_atlas/prepare/entry_relationship_mapper.py
google/datacatalog_connectors/apache_atlas/scrape/__init__.py
google/datacatalog_connectors/apache_atlas/scrape/apache_atlas_event_facade.py
google/datacatalog_connectors/apache_atlas/scrape/apache_atlas_facade.py
google/datacatalog_connectors/apache_atlas/scrape/metadata_enricher.py
google/datacatalog_connectors/apache_atlas/scrape/metadata_event_enricher.py
google/datacatalog_connectors/apache_atlas/scrape/metadata_event_scraper.py
google/datacatalog_connectors/apache_atlas/scrape/metadata_scraper.py
google/datacatalog_connectors/apache_atlas/sync/__init__.py
google/datacatalog_connectors/apache_atlas/sync/metadata_event_synchronizer.py
google/datacatalog_connectors/apache_atlas/sync/metadata_synchronizer.py
google_datacatalog_apache_atlas_connector-0.6.0.dist-info/METADATA
google_datacatalog_apache_atlas_connector-0.6.0.dist-info/WHEEL
google_datacatalog_apache_atlas_connector-0.6.0.dist-info/entry_points.txt
google_datacatalog_apache_atlas_connector-0.6.0.dist-info/namespace_packages.txt
google_datacatalog_apache_atlas_connector-0.6.0.dist-info/top_level.txt
google_datacatalog_apache_atlas_connector-0.6.0.dist-info/RECORD
