Metadata-Version: 2.1
Name: google-datacatalog-apache-atlas-connector
Version: 0.6.0
Summary: Package for ingesting Apache Atlas metadata into Google Cloud Data Catalog
Home-page: UNKNOWN
Author: Google LLC
License: UNKNOWN
Platform: Posix; MacOS X; Windows
Classifier: Development Status :: 4 - Beta
Classifier: Programming Language :: Python :: 3.7
Requires-Dist: atlasclient
Requires-Dist: kafka-python
Requires-Dist: google-datacatalog-connectors-commons (>=0.6.0)
